LICENSE
gpt3_tokenizer/__init__.py
gpt3_tokenizer/_entry.py
gpt3_tokenizer/_functions.py
gpt3_tokenizer/data/encoder.json
gpt3_tokenizer/data/vocab.bpe
gpt3_tokenizer-0.1.5.dist-info/LICENSE
gpt3_tokenizer-0.1.5.dist-info/METADATA
gpt3_tokenizer-0.1.5.dist-info/WHEEL
gpt3_tokenizer-0.1.5.dist-info/RECORD
