Metadata-Version: 2.1
Name: gpt3_tokenizer
Version: 0.1.5
Summary: Encoder/Decoder and tokens counter for GPT3
Home-page: https://github.com/alisonjf/gpt3-tokenizer
License: MIT
Keywords: openai,gpt,gpt-3,gpt3,gpt4,gpt-4,tokenizer
Author: Alison Ferrenha
Requires-Python: >=2.7, !=3.0.*, !=3.1.*, !=3.2.*
Classifier: License :: OSI Approved :: MIT License
Classifier: Operating System :: OS Independent
Classifier: Programming Language :: Python
Classifier: Programming Language :: Python :: 2
Classifier: Programming Language :: Python :: 2.7
Classifier: Programming Language :: Python :: 3
Classifier: Programming Language :: Python :: 3.4
Classifier: Programming Language :: Python :: 3.5
Classifier: Programming Language :: Python :: 3.6
Classifier: Programming Language :: Python :: 3.7
Classifier: Programming Language :: Python :: 3.8
Classifier: Programming Language :: Python :: 3.9
Classifier: Programming Language :: Python :: 3.10
Classifier: Programming Language :: Python :: 3.11
Classifier: Programming Language :: Python :: 3.12
Requires-Dist: future (>=0.18.3,<0.19.0)
Requires-Dist: regex (==2021.11.10) ; python_version < "3"
Requires-Dist: regex ; python_version >= "3"
Requires-Dist: six (>=1.16.0,<2.0.0)
Project-URL: Repository, https://github.com/alisonjf/gpt3-tokenizer
